odoo/addons/mrp_warehouse_calendar/README.rst
odoo/addons/mrp_warehouse_calendar/__init__.py
odoo/addons/mrp_warehouse_calendar/__manifest__.py
odoo/addons/mrp_warehouse_calendar/i18n/de.po
odoo/addons/mrp_warehouse_calendar/i18n/mrp_warehouse_calendar.pot
odoo/addons/mrp_warehouse_calendar/models/__init__.py
odoo/addons/mrp_warehouse_calendar/models/mrp_production.py
odoo/addons/mrp_warehouse_calendar/models/procurement_rule.py
odoo/addons/mrp_warehouse_calendar/readme/CONFIGURE.rst
odoo/addons/mrp_warehouse_calendar/readme/CONTRIBUTORS.rst
odoo/addons/mrp_warehouse_calendar/readme/DESCRIPTION.rst
odoo/addons/mrp_warehouse_calendar/readme/USAGE.rst
odoo/addons/mrp_warehouse_calendar/static/description/icon.png
odoo/addons/mrp_warehouse_calendar/static/description/index.html
odoo/addons/mrp_warehouse_calendar/tests/__init__.py
odoo/addons/mrp_warehouse_calendar/tests/test_mrp_warehouse_calendar.py
odoo11_addon_mrp_warehouse_calendar-11.0.1.0.0.99.dev8.dist-info/METADATA
odoo11_addon_mrp_warehouse_calendar-11.0.1.0.0.99.dev8.dist-info/WHEEL
odoo11_addon_mrp_warehouse_calendar-11.0.1.0.0.99.dev8.dist-info/top_level.txt
odoo11_addon_mrp_warehouse_calendar-11.0.1.0.0.99.dev8.dist-info/RECORD
